tfidf_transformer_afiniti/__init__.py
tfidf_transformer_afiniti/main.py
tfidf_transformer_afiniti/tfidf_test.py
tfidf_transformer_afiniti-0.4.dist-info/METADATA
tfidf_transformer_afiniti-0.4.dist-info/WHEEL
tfidf_transformer_afiniti-0.4.dist-info/top_level.txt
tfidf_transformer_afiniti-0.4.dist-info/RECORD
