Metadata-Version: 2.1
Name: tfidf-transformer-afiniti
Version: 0.4
Summary: A package for performing TF-IDF transformation on text data
Home-page: https://github.com/yunusemreemik/tfidf_afiniti.git
Author: Yunus Emre Emik
Author-email: yunus_emre3497@hotmail.com
Requires-Dist: scikit-learn
